LICENSE
README.md
setup.py
stlpy/__init__.py
stlpy.egg-info/PKG-INFO
stlpy.egg-info/SOURCES.txt
stlpy.egg-info/dependency_links.txt
stlpy.egg-info/not-zip-safe
stlpy.egg-info/requires.txt
stlpy.egg-info/top_level.txt
stlpy/STL/__init__.py
stlpy/STL/formula.py
stlpy/STL/predicate.py
stlpy/benchmarks/__init__.py
stlpy/benchmarks/base.py
stlpy/benchmarks/common.py
stlpy/benchmarks/door_puzzle.py
stlpy/benchmarks/either_or.py
stlpy/benchmarks/narrow_passage.py
stlpy/benchmarks/nonlinear_reach_avoid.py
stlpy/benchmarks/random_multitarget.py
stlpy/benchmarks/reach_avoid.py
stlpy/benchmarks/stepping_stones.py
stlpy/solvers/__init__.py
stlpy/solvers/base.py
stlpy/solvers/drake/__init__.py
stlpy/solvers/drake/drake_base.py
stlpy/solvers/drake/drake_micp.py
stlpy/solvers/drake/drake_smooth.py
stlpy/solvers/drake/drake_sos1.py
stlpy/solvers/gurobi/__init__.py
stlpy/solvers/gurobi/gurobi_micp.py
stlpy/solvers/scipy/__init__.py
stlpy/solvers/scipy/gradient_solver.py
stlpy/systems/__init__.py
stlpy/systems/linear.py
stlpy/systems/nonlinear.py