Metadata-Version: 2.1
Name: stlpy
Version: 0.2.1
Summary: A Python library for control from Signal Temporal Logic (STL) specifications
Home-page: https://stlpy.readthedocs.io/en/latest/index.html
Author: Vince Kurtz
Author-email: vjkurtz@gmail.com
License: MIT
Project-URL: Source Code, https://github.com/vincekurtz/stlpy
Project-URL: Documentation, https://stlpy.readthedocs.io/en/latest/index.html
Platform: UNKNOWN
Requires-Python: >=3.8
